Calculator/ASCII .py
Calculator/Mortgage.py
Calculator/Quadratic_Equation.py
Calculator/__init__.py
Calculator/bmi.py
Calculator/conject.py
Calculator/grade.py
Calculator/graph.py
Calculator/int_diff.py
Calculator/mega_calculator.py
Calculator/number_base.py
Calculator/roman_number.py
Calculator/sequence.py
Calculator/special_relativity_calculator.py
Calculator/stock.py
Calculator/sudoku.py
Calculator/time.py
Calculator/time_calulator.py
GUI/A_basic_gui_calculator.py
GUI/Form.py
GUI/Pikachu.py
GUI/Quiz.py
GUI/__init__.py
GUI/clender.py
GUI/clock.py
GUI/doraemon.py
GUI/file_explorer.py
GUI/graphics.py
GUI/happy_birth_day.py
GUI/notepad.py
GUI/paint.py
GUI/rainbow.py
GUI/search_applications.py
GUI/snake_ladder.py
GUI/spelling.py
GUI/spinner.py
GUI/tick_cross.py
GUI/todo.py
GUI/youtube_download.py
Game/__init__.py
Game/blocks.py
Game/color_guessing.py
Game/colox.py
Game/dice.py
Game/hangman.py
Game/master_mid.py
Game/number_details.py
Game/number_guessing.py
Game/rock_paper_scissors.py
Game/snake_game.py
Game/snake_ladder.py
Game/star.py
Game/tick_cross.py
Game/tick_cross_gui.py
Game/twenty_one.py
Game/typing_speed.py
Utilities/__init__.py
Utilities/birthday.py
Utilities/browser.py
Utilities/btc.py
Utilities/connectivity.py
Utilities/count_down.py
Utilities/github.py
Utilities/google.py
Utilities/inta.py
Utilities/network.py
Utilities/password.py
Utilities/password_hash.py
Utilities/password_manager.py
Utilities/passwrd_generator.py
Utilities/secret_code.py
Utilities/short_form.py
Utilities/transfer.py
Utilities/url.py
Utilities/whatsapp_spam.py
Utilities/word_count.py
machine_learning/__init__.py
machine_learning/brightness_controllor.py
machine_learning/camera.py
machine_learning/crypto_prices.py
machine_learning/eye_blink.py
machine_learning/gold_price.py
machine_learning/lang_dect.py
machine_learning/sentiments.py
machine_learning/sketch.py
machine_learning/spam_dect.py
machine_learning/text_to_speech.py
python_projects-0.5.dist-info/LICENSE
python_projects-0.5.dist-info/METADATA
python_projects-0.5.dist-info/WHEEL
python_projects-0.5.dist-info/top_level.txt
python_projects-0.5.dist-info/RECORD
